Metadata-Version: 2.3
Name: graphragkhoj
Version: 1.0.0
Summary: GraphRAG: A graph-based retrieval-augmented generation (RAG) system.
License: MIT
Author: Your Name
Author-email: your_email@example.com
Requires-Python: >=3.10,<3.13
Classifier: License :: OSI Approved :: MIT License
Classifier: Programming Language :: Python :: 3
Classifier: Programming Language :: Python :: 3.10
Classifier: Programming Language :: Python :: 3.11
Classifier: Programming Language :: Python :: 3.12
Requires-Dist: aiofiles (>=24.1.0,<25.0.0)
Requires-Dist: azure-cosmos (>=4.9.0,<5.0.0)
Requires-Dist: azure-identity (>=1.19.0,<2.0.0)
Requires-Dist: azure-search-documents (>=11.5.2,<12.0.0)
Requires-Dist: azure-storage-blob (>=12.24.0,<13.0.0)
Requires-Dist: devtools (>=0.12.2,<0.13.0)
Requires-Dist: environs (>=11.0.0,<12.0.0)
Requires-Dist: fnllm[azure,openai] (>=0.3.0,<0.4.0)
Requires-Dist: future (>=1.0.0,<2.0.0)
Requires-Dist: graspologic (>=3.4.1,<4.0.0)
Requires-Dist: json-repair (>=0.30.3,<0.31.0)
Requires-Dist: lancedb (>=0.17.0,<0.18.0)
Requires-Dist: networkx (>=3.4.2,<4.0.0)
Requires-Dist: nltk (==3.9.1)
Requires-Dist: numpy (>=1.25.2,<2.0.0)
Requires-Dist: openai (>=1.68.0,<2.0.0)
Requires-Dist: pandas (>=2.2.3,<3.0.0)
Requires-Dist: pyarrow (>=17.0.0)
Requires-Dist: pydantic (>=2.10.3,<3.0.0)
Requires-Dist: python-dotenv (>=1.0.1,<2.0.0)
Requires-Dist: pyyaml (>=6.0.2,<7.0.0)
Requires-Dist: rich (>=13.9.4,<14.0.0)
Requires-Dist: spacy (>=3.8.4,<4.0.0)
Requires-Dist: textblob (>=0.18.0.post0,<0.19.0)
Requires-Dist: tiktoken (>=0.9.0,<0.10.0)
Requires-Dist: tqdm (>=4.67.1,<5.0.0)
Requires-Dist: typer (>=0.15.1,<0.16.0)
Requires-Dist: typing-extensions (>=4.12.2,<5.0.0)
Requires-Dist: umap-learn (>=0.5.6,<0.6.0)
Project-URL: Bug Tracker, https://github.com/microsoft/graphrag/issues
Project-URL: Source, https://github.com/microsoft/graphrag
